{"type": "FeatureCollection", "features": [{"type": "Feature", "properties": {"Unnamed: 0": 13, "FID": 13.0, "ST": 1.0, "STATE": "ALABAMA", "ST_ABBR": "AL", "COUNTY": "Lauderdale", "FIPS": "01077", "LOCATION": "Lauderdale County, Alabama", "AREA_SQMI": 667.699346956, "E_TOTPOP": 92641.0, "E_HU": 44313.0, "E_HH": 38361.0, "E_POV": 16538.0, "E_UNEMP": 3249.0, "E_PCI": 24893.0, "E_NOHSDP": 9559.0, "E_AGE65": 16965.0, "E_AGE17": 19004.0, "E_DISABL": 14331.0, "E_SNGPNT": 3025.0, "E_MINRTY": 13904.0, "E_LIMENG": 503.0, "E_MUNIT": 2227.0, "E_MOBILE": 4311.0, "E_CROWD": 463.0, "E_NOVEH": 2891.0, "E_GROUPQ": 2111.0, "EP_POV": 18.3, "MP_POV": 1.6, "EP_UNEMP": 7.6, "MP_UNEMP": 1.0, "EP_PCI": 24893.0, "MP_PCI": 872.0, "EP_NOHSDP": 15.1, "MP_NOHSDP": 1.1, "EP_AGE65": 18.3, "MP_AGE65": 0.1, "EP_AGE17": 20.5, "MP_AGE17": 0.0, "EP_DISABL": 15.6, "MP_DISABL": 1.0, "EP_SNGPNT": 7.9, "MP_SNGPNT": 0.9, "EP_MINRTY": 15.0, "MP_MINRTY": 0.1, "EP_LIMENG": 0.6, "MP_LIMENG": 0.2, "EP_MUNIT": 5.0, "MP_MUNIT": 0.7, "EP_MOBILE": 9.7, "MP_MOBILE": 1.0, "EP_CROWD": 1.2, "MP_CROWD": 0.5, "EP_NOVEH": 7.5, "MP_NOVEH": 0.9, "EP_GROUPQ": 2.3, "MP_GROUPQ": 0.3, "EPL_POV": 0.6651, "EPL_UNEMP": 0.6078, "EPL_PCI": 0.4546, "EPL_NOHSDP": 0.6125, "SPL_THEME1": 2.34, "RPL_THEME1": 0.6097, "EPL_AGE65": 0.6049, "EPL_AGE17": 0.2512, "EPL_DISABL": 0.5218, "EPL_SNGPNT": 0.4101, "SPL_THEME2": 1.788, "RPL_THEME2": 0.32, "EPL_MINRTY": 0.4884, "EPL_LIMENG": 0.4209, "SPL_THEME3": 0.9093, "RPL_THEME3": 0.4429, "EPL_MUNIT": 0.7090000000000001, "EPL_MOBILE": 0.4483, "EPL_CROWD": 0.242, "EPL_NOVEH": 0.7284, "EPL_GROUPQ": 0.5657, "SPL_THEME4": 2.6934, "RPL_THEME4": 0.5868, "SPL_THEMES": 7.7307, "RPL_THEMES": 0.5396, "E_UNINSUR": 10115.0, "EP_UNINSUR": 11.0, "MP_UNINSUR": 1.0, "E_DAYPOP": 85031.0, "County": "Lauderdale County, AL", "County Code": 1077.0, "Total_Deaths": 1161.0, "Population": 92318.0, "Total_Death_Rate": 12.576095669316926, "Accident_Deaths": 50.0, "Accident_Death_Rate": 0.5416061873090838, "Alzheimer_Deaths": 82.0, "Alzheimer_Death_Rate": 0.8882341471868974, "Cancer_Deaths": 217.0, "Cancer_Death_Rate": 2.350570852921424, "Diabetes_Deaths": 12.0, "Diabetes_Death_Rate": 0.1299854849541801, "Flu_Deaths": 29.0, "Flu_Death_Rate": 0.3141315886392686, "Heart_Deaths": 291.0, "Heart_Death_Rate": 3.1521480101388675, "Kidney_Deaths": 26.0, "Kidney_Death_Rate": 0.2816352174007236, "LowerResp_Deaths": 70.0, "LowerResp_Death_Rate": 0.7582486622327174, "Stroke_Deaths": 65.0, "Stroke_Death_Rate": 0.7040880435018091, "Suicide_Deaths": 20.0, "Suicide_Death_Rate": 0.21664247492363356, "Location": "Lauderdale County, Alabama", "Life Expectancy": 76.5, "County name": "AL-Lauderdale County", "Total per enrollee (age, sex, race adjusted)": "7,983 ", "Total per enrollee (age, sex, race, price adjusted)": "9,753 "}, "geometry": {"type": "Polygon", "coordinates": [[[-87.25419212271107, 34.75812977692779], [-87.2701380276974, 34.74844066021625], [-87.2885177382604, 34.75151522995667], [-87.34626582498336, 34.80755564832373], [-87.38540564172136, 34.80963071092731], [-87.4250492009388, 34.79308289480679], [-87.5137734094334, 34.8259609500822], [-87.5530121718867, 34.824801472071584], [-87.70316985827367, 34.774060037094216], [-87.76493923355771, 34.74001478500631], [-87.80856517650263, 34.740198067697825], [-87.85845479765958, 34.76180423744486], [-87.92058167261976, 34.815800364807764], [-87.9392886811039, 34.859653313053485], [-87.96007888542582, 34.884906124548415], [-88.02801242336214, 34.90803061888723], [-88.09046866840505, 34.89562966431938], [-88.10888650674107, 34.89993644494179], [-88.14310493973281, 34.93031246872061], [-88.19399360179024, 35.004453632898304], [-88.1949623891317, 35.01354384310994], [-87.98607824493303, 35.01603364885324], [-87.60781307500223, 35.0105466168004], [-87.2227639070873, 35.007346215048194], [-87.20758848357947, 35.00796040373973], [-87.21484545244363, 34.82051406615993], [-87.24252616385472, 34.79333870315351], [-87.26523964494466, 34.782417427364024], [-87.25419212271107, 34.75812977692779]]]}}, {"type": "Feature", "properties": {"Unnamed: 0": 15, "FID": 15.0, "ST": 1.0, "STATE": "ALABAMA", "ST_ABBR": "AL", "COUNTY": "Limestone", "FIPS": "01083", "LOCATION": "Limestone County, Alabama", "AREA_SQMI": 559.939197679, "E_TOTPOP": 90257.0, "E_HU": 35515.0, "E_HH": 32073.0, "E_POV": 12290.0, "E_UNEMP": 3304.0, "E_PCI": 26086.0, "E_NOHSDP": 10449.0, "E_AGE65": 12555.0, "E_AGE17": 21104.0, "E_DISABL": 13193.0, "E_SNGPNT": 2521.0, "E_MINRTY": 20365.0, "E_LIMENG": 1030.0, "E_MUNIT": 1174.0, "E_MOBILE": 4381.0, "E_CROWD": 646.0, "E_NOVEH": 1458.0, "E_GROUPQ": 2940.0, "EP_POV": 14.1, "MP_POV": 1.6, "EP_UNEMP": 7.9, "MP_UNEMP": 1.2, "EP_PCI": 26086.0, "MP_PCI": 1006.0, "EP_NOHSDP": 16.8, "MP_NOHSDP": 1.3, "EP_AGE65": 13.9, "MP_AGE65": 0.1, "EP_AGE17": 23.4, "MP_AGE17": 0.1, "EP_DISABL": 15.1, "MP_DISABL": 1.1, "EP_SNGPNT": 7.9, "MP_SNGPNT": 1.1, "EP_MINRTY": 22.6, "MP_MINRTY": 0.1, "EP_LIMENG": 1.2, "MP_LIMENG": 0.4, "EP_MUNIT": 3.3, "MP_MUNIT": 0.6, "EP_MOBILE": 12.3, "MP_MOBILE": 1.3, "EP_CROWD": 2.0, "MP_CROWD": 0.6, "EP_NOVEH": 4.5, "MP_NOVEH": 0.9, "EP_GROUPQ": 3.3, "MP_GROUPQ": 0.6, "EPL_POV": 0.398, "EPL_UNEMP": 0.6466, "EPL_PCI": 0.3668, "EPL_NOHSDP": 0.6925, "SPL_THEME1": 2.1038, "RPL_THEME1": 0.5431, "EPL_AGE65": 0.1885, "EPL_AGE17": 0.6221, "EPL_DISABL": 0.4731, "EPL_SNGPNT": 0.4059, "SPL_THEME2": 1.6896, "RPL_THEME2": 0.2541, "EPL_MINRTY": 0.6084, "EPL_LIMENG": 0.6374, "SPL_THEME3": 1.2458, "RPL_THEME3": 0.6412, "EPL_MUNIT": 0.5549, "EPL_MOBILE": 0.5539999999999999, "EPL_CROWD": 0.5384, "EPL_NOVEH": 0.263, "EPL_GROUPQ": 0.7004, "SPL_THEME4": 2.6106, "RPL_THEME4": 0.5409, "SPL_THEMES": 7.6498, "RPL_THEMES": 0.5269, "E_UNINSUR": 10913.0, "EP_UNINSUR": 12.5, "MP_UNINSUR": 1.3, "E_DAYPOP": 80048.0, "County": "Limestone County, AL", "County Code": 1083.0, "Total_Deaths": 727.0, "Population": 92753.0, "Total_Death_Rate": 7.838021411706362, "Accident_Deaths": 36.0, "Accident_Death_Rate": 0.3881276077323644, "Alzheimer_Deaths": 35.0, "Alzheimer_Death_Rate": 0.3773462852953543, "Cancer_Deaths": 182.0, "Cancer_Death_Rate": 1.9622006835358423, "Diabetes_Deaths": 